streamlit_split_button/__init__.py
streamlit_split_button/example.py
streamlit_split_button-0.1.0.dist-info/METADATA
streamlit_split_button-0.1.0.dist-info/WHEEL
streamlit_split_button-0.1.0.dist-info/licenses/LICENSE
streamlit_split_button-0.1.0.dist-info/RECORD
