Metadata-Version: 2.4
Name: streamlit-split-button
Version: 0.1.0
Summary: A beautiful split button component for Streamlit that combines a primary action button with a dropdown menu. Perfect for providing users with a main action while offering alternative options in an elegant, space-efficient design.
License: Apache-2.0
License-File: LICENSE
Keywords: streamlit,python,material,button,component
Author: Jonathan Alles
Author-email: Jonathan.Alles@evo-byte.com
Requires-Python: >=3.11
Classifier: License :: OSI Approved :: Apache Software License
Classifier: Programming Language :: Python
Classifier: Programming Language :: Python :: 3
Classifier: Programming Language :: Python :: 3.11
Classifier: Programming Language :: Python :: 3.12
Classifier: Programming Language :: Python :: 3.13
Classifier: Programming Language :: Python :: 3.14
Classifier: Programming Language :: Python :: 3.15
Classifier: Topic :: Internet :: WWW/HTTP
Classifier: Topic :: Internet :: WWW/HTTP :: Browsers
Classifier: Topic :: Software Development :: Libraries :: Python Modules
Requires-Dist: streamlit (>=1.43)
Project-URL: Homepage, https://www.evo-byte.com
Project-URL: Repository, https://github.com/EvobyteDigitalBiology/streamlit-redirect
